LICENSE.txt
MANIFEST.in
README.txt
__init__.py
dictset.py
setup.py
test__dictset.py
dictset.egg-info/PKG-INFO
dictset.egg-info/SOURCES.txt
dictset.egg-info/dependency_links.txt
dictset.egg-info/top_level.txt
doc/conf.py